omoidasu/__init__.py
omoidasu/cli.py
omoidasu/commands.py
omoidasu/config.py
omoidasu/crud.py
omoidasu/exceptions.py
omoidasu/models.py
omoidasu/utils.py
omoidasu-0.4.10.dist-info/entry_points.txt
omoidasu-0.4.10.dist-info/WHEEL
omoidasu-0.4.10.dist-info/METADATA
omoidasu-0.4.10.dist-info/RECORD
