Metadata-Version: 2.1
Name: omoidasu
Version: 0.4.10
Summary: CLI flashcards tool.
Home-page: https://github.com/0djentd/omoidasu
Author: 0djentd
Requires-Python: >=3.8,<4.0
Classifier: Programming Language :: Python :: 3
Classifier: Programming Language :: Python :: 3.10
Classifier: Programming Language :: Python :: 3.8
Classifier: Programming Language :: Python :: 3.9
Requires-Dist: appdirs (>=1.4.4,<2.0.0)
Requires-Dist: click (>=8.1.3,<9.0.0)
Requires-Dist: pydantic (>=1.9.1,<2.0.0)
Requires-Dist: rich (>=12.4.4,<13.0.0)
Project-URL: Repository, https://github.com/0djentd/omoidasu
